llmpipeline/__init__.py
llmpipeline/log.py
llmpipeline/pipe.py
llmpipeline/pipeline.py
llmpipeline/prompt.py
llmpipeline/utils.py
llmpipeline-0.0.6.dist-info/LICENSE
llmpipeline-0.0.6.dist-info/METADATA
llmpipeline-0.0.6.dist-info/WHEEL
llmpipeline-0.0.6.dist-info/top_level.txt
llmpipeline-0.0.6.dist-info/RECORD
