Metadata-Version: 2.1
Name: llmpipeline
Version: 0.0.6
Summary: LLMPipeline is a Python package designed to optimize the performance of tasks related to Large Language Models (LLMs)
Home-page: https://github.com/new-soul-house/LLMPipeline
Author: linluhe
Author-email: is4test@163.com
Classifier: Programming Language :: Python :: 3
Classifier: License :: OSI Approved :: MIT License
Classifier: Operating System :: OS Independent
Requires-Python: >=3.10
License-File: LICENSE
Requires-Dist: rich
